mqtt_logger/__init__.py
mqtt_logger/logger.py
muxu_io_mqtt_logger-1.3.0.dist-info/licenses/LICENSE
muxu_io_mqtt_logger-1.3.0.dist-info/METADATA
muxu_io_mqtt_logger-1.3.0.dist-info/WHEEL
muxu_io_mqtt_logger-1.3.0.dist-info/top_level.txt
muxu_io_mqtt_logger-1.3.0.dist-info/RECORD
