Metadata-Version: 2.4
Name: muxu-io-mqtt-logger
Version: 1.3.0
Summary: A logger that logs messages to an MQTT topic with systemd journal integration
Home-page: https://github.com/muxu-io/mqtt-logger
Author: Alex Gonzalez
Author-email: Alex Gonzalez <alex@muxu.io>
License: MIT
Classifier: Programming Language :: Python :: 3
Classifier: Programming Language :: Python :: 3.7
Classifier: Programming Language :: Python :: 3.8
Classifier: Programming Language :: Python :: 3.9
Classifier: Programming Language :: Python :: 3.10
Classifier: Programming Language :: Python :: 3.11
Classifier: Programming Language :: Python :: 3.12
Classifier: License :: OSI Approved :: MIT License
Classifier: Operating System :: POSIX :: Linux
Classifier: Development Status :: 4 - Beta
Classifier: Intended Audience :: Developers
Classifier: Topic :: Software Development :: Libraries :: Python Modules
Classifier: Topic :: System :: Logging
Classifier: Topic :: Communications
Requires-Python: >=3.7
License-File: LICENSE
Requires-Dist: paho-mqtt>=1.6.1
Requires-Dist: systemd-python<235,>=234
Requires-Dist: muxu-io-mqtt-connector
Provides-Extra: dev
Requires-Dist: pytest>=7.0.0; extra == "dev"
Requires-Dist: pytest-cov>=4.0.0; extra == "dev"
Requires-Dist: pytest-asyncio>=0.21.0; extra == "dev"
Requires-Dist: black>=23.0.0; extra == "dev"
Requires-Dist: ruff>=0.1.0; extra == "dev"
Requires-Dist: bandit[toml]>=1.7.0; extra == "dev"
Requires-Dist: pip-audit>=2.6.0; extra == "dev"
Dynamic: author
Dynamic: home-page
Dynamic: license-file
Dynamic: requires-python
